socketgame/__init__.py
socketgame/base.py
socketgame/client.py
socketgame/connection.py
socketgame/server.py
socketgame-1.4.0.dist-info/LICENSE
socketgame-1.4.0.dist-info/METADATA
socketgame-1.4.0.dist-info/WHEEL
socketgame-1.4.0.dist-info/top_level.txt
socketgame-1.4.0.dist-info/RECORD
