Metadata-Version: 2.1
Name: socketgame
Version: 1.4.0
Summary: Create fast LAN games easily
Home-page: https://github.com/CircuitSacul/SocketGame
Author: Lucas D
Author-email: circuitsacul@gmail.com
License: MIT
Platform: UNKNOWN
Classifier: License :: OSI Approved :: MIT License
Classifier: Programming Language :: Python :: 3
Classifier: Programming Language :: Python :: 3.7
